README.rst
setup.py
mcash/__init__.py
mcash/mapi_client/__init__.py
mcash/mapi_client/auth.py
mcash/mapi_client/mapi_client.py
mcash/mapi_client/mapi_client_example.py
mcash/mapi_client/mapi_error.py
mcash/mapi_client/mapi_response.py
mcash/mapi_client/pusherconnector.py
mcash/mapi_client/validation.py
mcash/mapi_client/backends/__init__.py
mcash/mapi_client/backends/requests.py
mcash/mapi_client/backends/requestsframework.py
mcash/mapi_client/backends/urlfetch.py
mcash_mapi_client.egg-info/PKG-INFO
mcash_mapi_client.egg-info/SOURCES.txt
mcash_mapi_client.egg-info/dependency_links.txt
mcash_mapi_client.egg-info/namespace_packages.txt
mcash_mapi_client.egg-info/requires.txt
mcash_mapi_client.egg-info/top_level.txt