Metadata-Version: 1.0
Name: mcash-mapi-client
Version: 0.1.3
Summary: Thin python wrapper around mCASH's merchant api
Home-page: https://github.com/mcash/merchant-api-python-sdk
Author: mCASH Norge AS
Author-email: sm@mcash.no
License: MIT
Platform: UNKNOWN
